empatches
