Metadata-Version: 2.1
Name: empatches
Version: 0.1.1
Summary: Extract and Merge image patches for easy, fast and self-contained digital image processing and deep learning model training.
Home-page: https://github.com/Mr-TalhaIlyas/EMPatches
Author: Talha Ilyas
Author-email: mr.talhailyas@gmail.com
License: UNKNOWN
Keywords: python,extract image patches,merge image patches,patchify,sliding window
Platform: UNKNOWN
Classifier: Intended Audience :: Education
Classifier: Programming Language :: Python :: 3
Classifier: License :: OSI Approved :: MIT License
Classifier: Operating System :: OS Independent
